mkpyez/__init__.py
mkpyez-0.2.dist-info/License.txt
mkpyez-0.2.dist-info/METADATA
mkpyez-0.2.dist-info/WHEEL
mkpyez-0.2.dist-info/top_level.txt
mkpyez-0.2.dist-info/RECORD
