Metadata-Version: 2.1
Name: mkpyez
Version: 0.2
Summary: this is made only for making work easy
Author: Shreyas Naik
License: MIT
License-File: License.txt
